MANIFEST.in
README.md
requirements.txt
setup.cfg
setup.py
djmyframework/.dockerignore
djmyframework/Dockerfile
djmyframework/__init__.py
djmyframework/asgi.py
djmyframework/celery_app.py
djmyframework/log_def.json
djmyframework/manage.py
djmyframework/mysupervisorctl.py
djmyframework/settings.py
djmyframework/urls.py
djmyframework/wsgi.py
djmyframework.egg-info/PKG-INFO
djmyframework.egg-info/SOURCES.txt
djmyframework.egg-info/dependency_links.txt
djmyframework.egg-info/entry_points.txt
djmyframework.egg-info/requires.txt
djmyframework.egg-info/top_level.txt
djmyframework/apps/__init__.py
djmyframework/apps/analysis/__init__.py
djmyframework/apps/analysis/admin.py
djmyframework/apps/analysis/admin_resource.py
djmyframework/apps/analysis/apps.py
djmyframework/apps/analysis/settings.py
djmyframework/apps/analysis/jinja2_templates/analysis/base.html
djmyframework/apps/analysis/jinja2_templates/analysis/query_template_edit.html
djmyframework/apps/analysis/jinja2_templates/analysis/query_view.html
djmyframework/apps/analysis/jinja2_templates/analysis/query_widget.html
djmyframework/apps/analysis/jinja2_templates/analysis/statistic_edit.html
djmyframework/apps/analysis/jinja2_templates/analysis/statistic_execute.html
djmyframework/apps/analysis/jinja2_templates/analysis/statistic_list.html
djmyframework/apps/analysis/jinja2_templates/analysis/old/base.html
djmyframework/apps/analysis/jinja2_templates/analysis/old/feedback.html
djmyframework/apps/analysis/jinja2_templates/analysis/old/header.html
djmyframework/apps/analysis/jinja2_templates/analysis/old/shangxia.html
djmyframework/apps/analysis/jinja2_templates/analysis/plugins/10分刷新.html
djmyframework/apps/analysis/jinja2_templates/analysis/plugins/IP解析.html
djmyframework/apps/analysis/jinja2_templates/analysis/plugins/KO合服.html
djmyframework/apps/analysis/jinja2_templates/analysis/plugins/SDK列表.html
djmyframework/apps/analysis/jinja2_templates/analysis/plugins/SDK版本列表.html
djmyframework/apps/analysis/jinja2_templates/analysis/plugins/VIP编辑.html
djmyframework/apps/analysis/jinja2_templates/analysis/plugins/datatable.html
djmyframework/apps/analysis/jinja2_templates/analysis/plugins/export.html
