Metadata-Version: 2.1
Name: djmyframework
Version: 0.1.43
Summary: django myframework
Home-page: https://github.com/xzregg/dj_myframework.git
Author: xzregg
Author-email: xzregg@gmail.com
License: UNKNOWN
Platform: UNKNOWN
Classifier: Programming Language :: Python :: 3
Classifier: License :: OSI Approved :: MIT License
Classifier: Operating System :: OS Independent
Requires-Python: >=3.6
